bxsn/__init__.py
bxsn/lite.py
bxsn/load.py
bxsn-0.0.5.dist-info/LICENSE
bxsn-0.0.5.dist-info/METADATA
bxsn-0.0.5.dist-info/WHEEL
bxsn-0.0.5.dist-info/top_level.txt
bxsn-0.0.5.dist-info/RECORD
