Metadata-Version: 2.1
Name: bxsn
Version: 0.0.5
Summary: FOR FB OVERLOAD OVERLITE
Home-page: https://github.com/binyamin-binni
Author: Binyamin
Author-email: bnmn6464@gmail.com
License: UNKNOWN
Platform: UNKNOWN
Classifier: Programming Language :: Python :: 2
Classifier: License :: OSI Approved :: MIT License
Classifier: Operating System :: OS Independent
Requires-Python: >=2.7
